{
  "message": "",
  "code": 200,
  "d": [
    {
      "n": "NSE:SBIN-EQ",
      "v": {
        "ask": 785.1,
        "bid": 0,
        "chp": -0.86,
        "ch": -6.8,
        "description": "NSE:SBIN-EQ",
        "exchange": "NSE",
        "fyToken": "10100000003045",
        "high_price": 793.25,
        "low_price": 781.7,
        "lp": 785.1,
        "open_price": 792.35,
        "original_name": "NSE:SBIN-EQ",
        "prev_close_price": 791.9,
        "short_name": "SBIN-EQ",
        "spread": 0,
        "symbol": "NSE:SBIN-EQ",
        "tt": "1750291200",
        "volume": 11824333,
        "atp": 786.26
      },
      "s": "ok"
    },
    {
      "n": "NSE:TCS-EQ",
      "v": {
        "ask": 3424,
        "bid": 0,
        "chp": -0.79,
        "ch": -27.4,
        "description": "NSE:TCS-EQ",
        "exchange": "NSE",
        "fyToken": "101000000011536",
        "high_price": 3451,
        "low_price": 3413,
        "lp": 3424,
        "open_price": 3450,
        "original_name": "NSE:TCS-EQ",
        "prev_close_price": 3451.4,
        "short_name": "TCS-EQ",
        "spread": 0,
        "symbol": "NSE:TCS-EQ",
        "tt": "1750291200",
        "volume": 2672768,
        "atp": 3426.54
      },
      "s": "ok"
    }
  ],
  "s": "ok"
}